Auto/Automation.py
Auto/__init__.py
Automation_vision-0.1.dist-info/LICENSE
Automation_vision-0.1.dist-info/METADATA
Automation_vision-0.1.dist-info/WHEEL
Automation_vision-0.1.dist-info/top_level.txt
Automation_vision-0.1.dist-info/RECORD
