Metadata-Version: 2.1
Name: Automation-vision
Version: 0.1
Summary: auto clicking and writing
Home-page: UNKNOWN
Author: AyazYousafxai
Author-email: ayazpk6630@gmail.com
License: MIT
Platform: UNKNOWN
Classifier: Programming Language :: Python :: 3
Classifier: Operating System :: Microsoft :: Windows
Classifier: License :: OSI Approved :: MIT License
Requires-Python: >=3.6
Requires-Dist: certifi (==2020.6.20)
Requires-Dist: chardet (==3.0.4)
Requires-Dist: idna (==2.10)
Requires-Dist: MouseInfo (==0.1.3)
Requires-Dist: numpy (==1.19.1)
Requires-Dist: opencv-python (==4.3.0.36)
Requires-Dist: pandas (==1.0.5)
Requires-Dist: Pillow (==7.2.0)
Requires-Dist: PyAutoGUI (==0.9.50)
Requires-Dist: PyGetWindow (==0.0.8)
Requires-Dist: PyMsgBox (==1.0.8)
Requires-Dist: pyperclip (==1.8.0)
Requires-Dist: PyRect (==0.1.4)
Requires-Dist: PyScreeze (==0.1.26)
Requires-Dist: python-dateutil (==2.8.1)
Requires-Dist: PyTweening (==1.0.3)
Requires-Dist: pytz (==2020.1)
Requires-Dist: pywin32 (==228)
Requires-Dist: six (==1.15.0)
Requires-Dist: urllib3 (==1.25.10)
